s3ala.py
s3ala-0.0.1.dist-info/METADATA
s3ala-0.0.1.dist-info/WHEEL
s3ala-0.0.1.dist-info/entry_points.txt
s3ala-0.0.1.dist-info/licenses/LICENSE
s3ala-0.0.1.dist-info/RECORD
