Metadata-Version: 2.1
Name: s3ala
Version: 0.0.1
Summary: A basic CLI-based aggregator to extract some very basic metrics from ALB logs stored in an S3 bucket
Project-URL: Source, https://github.com/uktrade/s3ala
Author-email: Department for International Trade <sre@digital.trade.gov.uk>
License-File: LICENSE
Classifier: License :: OSI Approved :: MIT License
Classifier: Operating System :: OS Independent
Classifier: Programming Language :: Python :: 3
Requires-Python: >=3.7
Requires-Dist: boto3>=1.34.41
Requires-Dist: click>=8.1.7
Requires-Dist: to-file-like-obj>=0.0.5
